opportunity_scraper/__init__.py
opportunity_scraper/govuk.py
opportunity_scraper/ktn.py
opportunity_scraper/opportunity.py
opportunity_scraper/settings.py
opportunity_scraper-0.1.6.dist-info/LICENSE.md
opportunity_scraper-0.1.6.dist-info/METADATA
opportunity_scraper-0.1.6.dist-info/WHEEL
opportunity_scraper-0.1.6.dist-info/entry_points.txt
opportunity_scraper-0.1.6.dist-info/top_level.txt
opportunity_scraper-0.1.6.dist-info/RECORD
