Metadata-Version: 2.1
Name: opportunity-scraper
Version: 0.1.6
Summary: Web scrapers for various innovation opportunity sites
Home-page: https://github.com/longsight/opportunity_scraper
Author: Ashleigh Crosby
Author-email: tcrosby@gmail.com
License: GPLv3+
Platform: UNKNOWN
Requires-Dist: requests
Requires-Dist: requests-oauthlib
Requires-Dist: selenium
